[{"id":"关卡编号","name":"关卡名称","bossShow":"本关BOSS形象","bossShowAdj":"BOSS形象调整","recHeroArray":"推荐英雄","buffHeroArray":"增益英雄类型","buffHeroAttArray":"增益属性","sceneLength":"关卡长度","sceneMap":"背景地图","createMonsterArray":"怪物分布","nodeText":"关卡攻略描述","expReward":"经验奖励","goldReward":"金钱奖励","starValue":"评价系数"},{"id":6001,"name":"铁壁之狱","bossShow":223,"bossShowAdj":-1.6,"recHeroArray":"80|124|156","buffHeroArray":"4841|5281|5601","buffHeroAttArray":"202|10000;6|3000","sceneLength":12,"sceneMap":"Map12","createMonsterArray":"25001|10000|7|1;25002|10000|7|2;25003|10000|7|3;25004|10000|8|2;25005|10000|9|2","nodeText":"本关卡怪物物理防御极高，建议使用法术攻击类英雄","expReward":0,"goldReward":3000,"starValue":20},{"id":6002,"name":"魔盾之狱","bossShow":203,"bossShowAdj":-1.55,"recHeroArray":"76|154|142","buffHeroArray":"4801|5461|5581","buffHeroAttArray":"202|10000;4|3000","sceneLength":12,"sceneMap":"Map12","createMonsterArray":"25006|10000|7|1;25007|10000|7|2;25008|10000|7|3;25009|10000|8|2;25010|10000|9|2","nodeText":"本关卡怪物法术防御极高，建议使用物理攻击类英雄","expReward":0,"goldReward":3000,"starValue":20},{"id":6003,"name":"利刃之狱","bossShow":7561,"bossShowAdj":-1.6,"recHeroArray":"78|146|144","buffHeroArray":"4821|5501|5481","buffHeroAttArray":"5|3000;7|3000;202|10000","sceneLength":12,"sceneMap":"Map12","createMonsterArray":"25011|10000|7|1;25012|10000|7|2;25013|10000|7|3;25014|10000|8|1;25015|10000|8|3","nodeText":"本关卡前排怪物攻击极高，建议使用防御型英雄顶住敌方攻击","expReward":0,"goldReward":3000,"starValue":20},{"id":6004,"name":"巫毒之狱","bossShow":5461,"bossShowAdj":-1.6,"recHeroArray":"14|118|174","buffHeroArray":"201|5221|7421","buffHeroAttArray":"8|3000;202|10000","sceneLength":12,"sceneMap":"Map12","createMonsterArray":"25016|10000|7|1;25017|10000|7|3;25018|10000|8|1;25019|10000|8|2;25020|10000|8|3","nodeText":"本关卡怪物擅长毒攻击，建议使用治疗类或可以解毒的英雄","expReward":0,"goldReward":3000,"starValue":20},{"id":6005,"name":"缚茧之狱","bossShow":5521,"bossShowAdj":-1.4,"recHeroArray":"82|150|172","buffHeroArray":"4861|5541|7401","buffHeroAttArray":"202|10000;14|-3000","sceneLength":12,"sceneMap":"Map12","createMonsterArray":"25021|10000|7|2;25022|10000|8|2;25023|10000|9|1;25024|10000|9|2;25025|10000|9|3","nodeText":"本关卡怪物擅长使用眩晕和封印攻击，建议使用速度更快的封印类英雄或解除封印类英雄","expReward":0,"goldReward":3000,"starValue":20}]