[{"id":"编号","type":"类型","num":"参数","name":"名称","text":"描述"},{"id":28,"type":1,"num":28,"name":"普通副本","text":"2-8 点醒悟空掉落"},{"id":48,"type":1,"num":48,"name":"普通副本","text":"3-8 八部天龙归位掉落"},{"id":63,"type":1,"num":63,"name":"普通副本","text":"4-3 黑熊精夺袈裟掉落"},{"id":68,"type":1,"num":68,"name":"普通副本","text":"4-8 再战黑熊精掉落"},{"id":88,"type":1,"num":88,"name":"普通副本","text":"5-8 唤醒净坛使者掉落"},{"id":104,"type":1,"num":104,"name":"普通副本","text":"6-4 一战黄风怪掉落"},{"id":106,"type":1,"num":106,"name":"普通副本","text":"6-6 再战黄风怪掉落"},{"id":108,"type":1,"num":108,"name":"普通副本","text":"6-8 三战黄风怪掉落"},{"id":128,"type":1,"num":128,"name":"普通副本","text":"7-8 点醒金身罗汉掉落"},{"id":148,"type":1,"num":148,"name":"普通副本","text":"8-8 白骨精现形掉落"},{"id":162,"type":1,"num":162,"name":"普通副本","text":"9-2 黄袍怪巡山掉落"},{"id":164,"type":1,"num":164,"name":"普通副本","text":"9-4 黄袍怪道真身掉落"},{"id":166,"type":1,"num":166,"name":"普通副本","text":"9-6 奎星君归位掉落"},{"id":183,"type":1,"num":183,"name":"普通副本","text":"10-3 初战金银角掉落"},{"id":186,"type":1,"num":186,"name":"普通副本","text":"10-6 棒杀老狐妖掉落"},{"id":187,"type":1,"num":187,"name":"普通副本","text":"10-7 再战金银角掉落"},{"id":188,"type":1,"num":188,"name":"普通副本","text":"10-8 绣花狐阿七掉落"},{"id":190,"type":1,"num":190,"name":"普通副本","text":"10-10 收服金银角掉落"},{"id":201,"type":1,"num":201,"name":"普通副本","text":"11-1 神秘的冤魂掉落"},{"id":203,"type":1,"num":203,"name":"普通副本","text":"11-3 路遇王子夜巡掉落"},{"id":205,"type":1,"num":205,"name":"普通副本","text":"11-5 揭露假国王掉落"},{"id":207,"type":1,"num":207,"name":"普通副本","text":"11-7 降服狮子精掉落"},{"id":222,"type":1,"num":222,"name":"普通副本","text":"12-2 剪径小魔头掉落"},{"id":224,"type":1,"num":224,"name":"普通副本","text":"12-4 神火助圣婴掉落"},{"id":226,"type":1,"num":226,"name":"普通副本","text":"12-6 收服红孩儿掉落"},{"id":242,"type":1,"num":242,"name":"普通副本","text":"13-2 偶遇三国师掉落"},{"id":244,"type":1,"num":244,"name":"普通副本","text":"13-4 妙计破虎仙掉落"},{"id":246,"type":1,"num":246,"name":"普通副本","text":"13-6 赌气鹿仙掉落"},{"id":248,"type":1,"num":248,"name":"普通副本","text":"13-8 油炸老羊仙掉落"},{"id":262,"type":1,"num":262,"name":"普通副本","text":"14-2 斑鳜精诈降掉落"},{"id":264,"type":1,"num":264,"name":"普通副本","text":"14-4 浑水现鱼精掉落"},{"id":266,"type":1,"num":266,"name":"普通副本","text":"14-6 金鱼精开溜掉落"},{"id":268,"type":1,"num":268,"name":"普通副本","text":"14-8 设计降鱼精掉落"},{"id":282,"type":1,"num":282,"name":"普通副本","text":"15-2 一战独角兕掉落"},{"id":284,"type":1,"num":284,"name":"普通副本","text":"15-4 二战独角兕掉落"},{"id":286,"type":1,"num":286,"name":"普通副本","text":"15-6 三战独角兕掉落"},{"id":302,"type":1,"num":302,"name":"普通副本","text":"16-2 抢占落胎泉掉落"},{"id":306,"type":1,"num":306,"name":"普通副本","text":"16-6 惊恐的女王掉落"},{"id":308,"type":1,"num":308,"name":"普通副本","text":"16-8 初战蝎子精掉落"},{"id":310,"type":1,"num":310,"name":"普通副本","text":"16-10 再战蝎子精掉落"},{"id":312,"type":1,"num":312,"name":"普通副本","text":"16-12 灭杀蝎子精掉落"},{"id":322,"type":1,"num":322,"name":"普通副本","text":"17-2 借宝扇遭拒掉落"},{"id":324,"type":1,"num":324,"name":"普通副本","text":"17-4 智取芭蕉扇掉落"},{"id":326,"type":1,"num":326,"name":"普通副本","text":"17-6 盛怒牛魔王掉落"},{"id":328,"type":1,"num":328,"name":"普通副本","text":"17-8 轻取玉面狐掉落"},{"id":330,"type":1,"num":330,"name":"普通副本","text":"17-10 大战牛魔王掉落"},{"id":342,"type":1,"num":342,"name":"普通副本","text":"18-2 舍利子被盗掉落"},{"id":344,"type":1,"num":344,"name":"普通副本","text":"18-4 质问老龙王掉落"},{"id":346,"type":1,"num":346,"name":"普通副本","text":"18-6 再捉九头虫掉落"},{"id":348,"type":1,"num":348,"name":"普通副本","text":"18-8 棒杀九头虫掉落"},{"id":361,"type":1,"num":361,"name":"普通副本","text":"19-1 对诗十八公掉落"},{"id":362,"type":1,"num":362,"name":"普通副本","text":"19-2 对诗孤直公掉落"},{"id":363,"type":1,"num":363,"name":"普通副本","text":"19-3 对诗凌空子掉落"},{"id":364,"type":1,"num":364,"name":"普通副本","text":"19-4 对诗拂云叟掉落"},{"id":365,"type":1,"num":365,"name":"普通副本","text":"19-5 对诗杏仙掉落"},{"id":366,"type":1,"num":366,"name":"普通副本","text":"19-6 激怒四老掉落"},{"id":368,"type":1,"num":368,"name":"普通副本","text":"19-8 脱身荆棘岭掉落"},{"id":382,"type":1,"num":382,"name":"普通副本","text":"20-2 狂傲黄眉怪掉落"},{"id":384,"type":1,"num":384,"name":"普通副本","text":"20-4 鏖战黄眉大王掉落"},{"id":386,"type":1,"num":386,"name":"普通副本","text":"20-6 替佛祖训徒掉落"},{"id":402,"type":1,"num":402,"name":"普通副本","text":"21-2 初遇赛太岁掉落"},{"id":404,"type":1,"num":404,"name":"普通副本","text":"21-4 再战赛太岁掉落"},{"id":406,"type":1,"num":406,"name":"普通副本","text":"21-6 降太岁救圣宫掉落"},{"id":421,"type":1,"num":421,"name":"普通副本","text":"22-1 濯垢泉遇妖掉落"},{"id":421,"type":1,"num":421,"name":"普通副本","text":"22-1 濯垢泉遇妖掉落"},{"id":423,"type":1,"num":423,"name":"普通副本","text":"22-3 大蛛女的诱惑掉落"},{"id":425,"type":1,"num":425,"name":"普通副本","text":"22-5 二蛛女的诱惑掉落"},{"id":427,"type":1,"num":427,"name":"普通副本","text":"22-7 小蛛女的诱惑掉落"},{"id":429,"type":1,"num":429,"name":"普通副本","text":"22-9 初战蜈蚣精掉落"},{"id":431,"type":1,"num":431,"name":"普通副本","text":"22-11 克杀蜈蚣精掉落"},{"id":442,"type":1,"num":442,"name":"普通副本","text":"23-2 吞天狮王掉落"},{"id":444,"type":1,"num":444,"name":"普通副本","text":"23-4 黄牙巨象掉落"},{"id":446,"type":1,"num":446,"name":"普通副本","text":"23-6 大鹏金翅掉落"},{"id":1012,"type":1,"num":1012,"name":"精英副本","text":"2-2 黑熊精夺袈裟掉落"},{"id":1015,"type":1,"num":1015,"name":"精英副本","text":"2-5 再战黑熊精掉落"},{"id":1022,"type":1,"num":1022,"name":"精英副本","text":"3-2 一战黄风怪掉落"},{"id":1023,"type":1,"num":1023,"name":"精英副本","text":"3-3 再战黄风怪掉落"},{"id":1024,"type":1,"num":1024,"name":"精英副本","text":"3-4 三战黄风怪掉落"},{"id":1034,"type":1,"num":1034,"name":"精英副本","text":"4-4 白骨精现形掉落"},{"id":1041,"type":1,"num":1041,"name":"精英副本","text":"5-1 黄袍怪巡山掉落"},{"id":1042,"type":1,"num":1042,"name":"精英副本","text":"5-2 黄袍怪道真身掉落"},{"id":1043,"type":1,"num":1043,"name":"精英副本","text":"5-3 奎星君归位掉落"},{"id":1055,"type":1,"num":1055,"name":"精英副本","text":"6-5 棒杀老狐妖掉落"},{"id":1056,"type":1,"num":1056,"name":"精英副本","text":"6-6 绣花狐阿七掉落"},{"id":1057,"type":1,"num":1057,"name":"精英副本","text":"6-7 收服金银角掉落"},{"id":1061,"type":1,"num":1061,"name":"精英副本","text":"7-1 神秘的冤魂掉落"},{"id":1062,"type":1,"num":1062,"name":"精英副本","text":"7-2 路遇王子夜巡掉落"},{"id":1063,"type":1,"num":1063,"name":"精英副本","text":"7-3 揭露假国王掉落"},{"id":1064,"type":1,"num":1064,"name":"精英副本","text":"7-4 降服狮子精掉落"},{"id":1071,"type":1,"num":1071,"name":"精英副本","text":"8-1 剪径小魔头掉落"},{"id":1072,"type":1,"num":1072,"name":"精英副本","text":"8-2 神火助圣婴掉落"},{"id":1073,"type":1,"num":1073,"name":"精英副本","text":"8-3 收服红孩儿掉落"},{"id":1081,"type":1,"num":1081,"name":"精英副本","text":"9-1 妙计破虎仙掉落"},{"id":1082,"type":1,"num":1082,"name":"精英副本","text":"9-2 赌气鹿仙掉落"},{"id":1083,"type":1,"num":1083,"name":"精英副本","text":"9-3 油炸老羊仙掉落"},{"id":1091,"type":1,"num":1091,"name":"精英副本","text":"10-1 斑鳜精诈降掉落"},{"id":1092,"type":1,"num":1092,"name":"精英副本","text":"10-2 浑水现鱼精掉落"},{"id":1093,"type":1,"num":1093,"name":"精英副本","text":"10-3 金鱼精开溜掉落"},{"id":1094,"type":1,"num":1094,"name":"精英副本","text":"10-4 设计降鱼精掉落"},{"id":1101,"type":1,"num":1101,"name":"精英副本","text":"11-1 一战独角兕掉落"},{"id":1102,"type":1,"num":1102,"name":"精英副本","text":"11-2 二战独角兕掉落"},{"id":1103,"type":1,"num":1103,"name":"精英副本","text":"11-3 三战独角兕掉落"},{"id":1111,"type":1,"num":1111,"name":"精英副本","text":"12-1 抢占落胎泉掉落"},{"id":1113,"type":1,"num":1113,"name":"精英副本","text":"12-3 惊恐的女王掉落"},{"id":1114,"type":1,"num":1114,"name":"精英副本","text":"12-4 初战蝎子精掉落"},{"id":1115,"type":1,"num":1115,"name":"精英副本","text":"12-5 再战蝎子精掉落"},{"id":1116,"type":1,"num":1116,"name":"精英副本","text":"12-6 灭杀蝎子精掉落"},{"id":1121,"type":1,"num":1121,"name":"精英副本","text":"13-1 借宝扇遭拒掉落"},{"id":1122,"type":1,"num":1122,"name":"精英副本","text":"13-2 智取芭蕉扇掉落"},{"id":1123,"type":1,"num":1123,"name":"精英副本","text":"13-3 盛怒牛魔王掉落"},{"id":1124,"type":1,"num":1124,"name":"精英副本","text":"13-4 轻取玉面狐掉落"},{"id":1125,"type":1,"num":1125,"name":"精英副本","text":"13-5 大战牛魔王掉落"},{"id":1131,"type":1,"num":1131,"name":"精英副本","text":"14-1 舍利子被盗掉落"},{"id":1132,"type":1,"num":1132,"name":"精英副本","text":"14-2 质问老龙王掉落"},{"id":1133,"type":1,"num":1133,"name":"精英副本","text":"14-3 再捉九头虫掉落"},{"id":1134,"type":1,"num":1134,"name":"精英副本","text":"14-4 棒杀九头虫掉落"},{"id":1141,"type":1,"num":1141,"name":"精英副本","text":"15-1 对诗十八公掉落"},{"id":1142,"type":1,"num":1142,"name":"精英副本","text":"15-2 对诗孤直公掉落"},{"id":1143,"type":1,"num":1143,"name":"精英副本","text":"15-3 对诗凌空子掉落"},{"id":1144,"type":1,"num":1144,"name":"精英副本","text":"15-4 对诗拂云叟掉落"},{"id":1145,"type":1,"num":1145,"name":"精英副本","text":"15-5 对诗杏仙掉落"},{"id":1146,"type":1,"num":1146,"name":"精英副本","text":"15-6 脱身荆棘岭掉落"},{"id":1151,"type":1,"num":1151,"name":"精英副本","text":"16-1 狂傲黄眉怪掉落"},{"id":1152,"type":1,"num":1152,"name":"精英副本","text":"16-2 鏖战黄眉大王掉落"},{"id":1153,"type":1,"num":1153,"name":"精英副本","text":"16-3 替佛祖训徒掉落"},{"id":1161,"type":1,"num":1161,"name":"精英副本","text":"17-1 初遇赛太岁掉落"},{"id":1162,"type":1,"num":1162,"name":"精英副本","text":"17-2 再战赛太岁掉落"},{"id":1163,"type":1,"num":1163,"name":"精英副本","text":"17-3 降太岁救圣宫掉落"},{"id":1171,"type":1,"num":1171,"name":"精英副本","text":"18-1 大蛛女的诱惑掉落"},{"id":1172,"type":1,"num":1172,"name":"精英副本","text":"18-2 二蛛女的诱惑掉落"},{"id":1173,"type":1,"num":1173,"name":"精英副本","text":"18-3 小蛛女的诱惑掉落"},{"id":1174,"type":1,"num":1174,"name":"精英副本","text":"18-4 初战蜈蚣精掉落"},{"id":1175,"type":1,"num":1175,"name":"精英副本","text":"18-5 克杀蜈蚣精掉落"},{"id":1181,"type":1,"num":1181,"name":"精英副本","text":"19-1 吞天狮王掉落"},{"id":1182,"type":1,"num":1182,"name":"精英副本","text":"19-2 黄牙巨象掉落"},{"id":1183,"type":1,"num":1183,"name":"精英副本","text":"19-3 大鹏金翅掉落"},{"id":2001,"type":2,"num":2001,"name":"活动副本","text":"蟠桃园抢桃掉落"},{"id":2021,"type":2,"num":2021,"name":"活动副本","text":"五庄观夺果掉落"},{"id":2041,"type":2,"num":2041,"name":"活动副本","text":"兜率宫偷丹掉落"},{"id":2081,"type":2,"num":2081,"name":"活动副本","text":"律法女娲掉落"},{"id":2082,"type":2,"num":2082,"name":"活动副本","text":"雷霆女娲掉落"},{"id":2083,"type":2,"num":2083,"name":"活动副本","text":"仙符女娲掉落"},{"id":2084,"type":2,"num":2084,"name":"活动副本","text":"拘魂女娲掉落"},{"id":2085,"type":2,"num":2085,"name":"活动副本","text":"净瓶女娲掉落"},{"id":2101,"type":2,"num":2101,"name":"活动副本","text":"幽冥秘宝掉落"},{"id":3001,"type":4,"num":0,"name":"魔神战","text":"打败魔神掉落"},{"id":3002,"type":5,"num":0,"name":"挖宝","text":"挖取藏宝图获得"},{"id":3003,"type":6,"num":1,"name":"钻石买碎片","text":"钻石购买碎片获得稀有英雄"},{"id":3004,"type":6,"num":2,"name":"金币买碎片","text":"金币购买碎片获得稀有英雄"},{"id":3005,"type":7,"num":0,"name":"神秘商店","text":"钻石购买神秘商店商品"},{"id":3006,"type":8,"num":0,"name":"积分商店","text":"PVP币兑换PVP积分商店商品"},{"id":3007,"type":9,"num":0,"name":"七天活动","text":"第一天礼包购买获得"},{"id":3008,"type":9,"num":0,"name":"七天活动","text":"第二天礼包购买获得"},{"id":3009,"type":9,"num":0,"name":"七天活动","text":"第三天礼包购买获得"},{"id":3010,"type":9,"num":0,"name":"七天活动","text":"第四天礼包购买获得"},{"id":3011,"type":9,"num":0,"name":"七天活动","text":"第五天礼包购买获得"},{"id":3012,"type":9,"num":0,"name":"七天活动","text":"第六天礼包购买获得"},{"id":3013,"type":9,"num":0,"name":"七天活动","text":"第七天礼包购买获得"},{"id":3014,"type":9,"num":0,"name":"签到奖励","text":"每日签到奖励"},{"id":3015,"type":9,"num":0,"name":"充值奖励","text":"每周充值奖励获得"},{"id":3016,"type":9,"num":0,"name":"舍利商店","text":"舍利购买舍利商店商品"},{"id":3017,"type":9,"num":0,"name":"开服活动","text":"开服7日活动专属英雄"},{"id":3018,"type":9,"num":0,"name":"PVP奖励","text":"PVP每周奖励英雄"},{"id":3019,"type":9,"num":0,"name":"传奇副本","text":"传奇副本通关奖励"},{"id":3020,"type":9,"num":0,"name":"炼狱之塔","text":"炼狱之塔奖励"},{"id":3021,"type":9,"num":0,"name":"主线任务","text":"战力成就任务奖励"},{"id":3022,"type":9,"num":0,"name":"守护城池","text":"守护城池挂机奖励"},{"id":3023,"type":9,"num":0,"name":"世界BOSS","text":"世界BOSS排名奖励"},{"id":3024,"type":9,"num":0,"name":"排行榜","text":"排行榜奖励"},{"id":3025,"type":9,"num":0,"name":"免费兑换","text":"收集指定英雄兑换"},{"id":3026,"type":9,"num":0,"name":"通关奖励","text":"通关副本并达到指定星数奖励"},{"id":3027,"type":9,"num":0,"name":"首通奖励","text":"首次通关指定副本奖励"},{"id":3028,"type":9,"num":0,"name":"主角英雄","text":"进入游戏选择主角时获得"},{"id":3029,"type":9,"num":0,"name":"VIP专属","text":"初级VIP专属英雄"},{"id":3030,"type":9,"num":0,"name":"VIP专属","text":"高级VIP专属英雄"},{"id":3031,"type":9,"num":0,"name":"VIP专属","text":"顶级VIP专属英雄"},{"id":3032,"type":9,"num":0,"name":"充值奖励","text":"首次购买各档次钻石奖励"},{"id":3033,"type":9,"num":0,"name":"首充奖励","text":"首次充值任意金额奖励"},{"id":3034,"type":9,"num":0,"name":"活动奖励","text":"不定期运营活动获得"},{"id":3035,"type":9,"num":0,"name":"首通奖励","text":"首次通关普通副本1至6奖励"},{"id":3036,"type":9,"num":0,"name":"首通奖励","text":"首次通关普通副本7至12奖励"},{"id":3037,"type":9,"num":0,"name":"首通奖励","text":"首次通关普通副本13至17奖励"},{"id":3038,"type":9,"num":0,"name":"首通奖励","text":"首次通关普通副本18至23奖励"},{"id":3039,"type":9,"num":0,"name":"首通奖励","text":"首次通关精英副本1至3奖励"},{"id":3040,"type":9,"num":0,"name":"首通奖励","text":"首次通关精英副本4至6奖励"},{"id":3041,"type":9,"num":0,"name":"首通奖励","text":"首次通关精英副本7至9奖励"},{"id":3042,"type":9,"num":0,"name":"首通奖励","text":"首次通关精英副本10至12奖励"},{"id":3043,"type":9,"num":0,"name":"首通奖励","text":"首次通关精英副本13至15奖励"},{"id":3044,"type":9,"num":0,"name":"首通奖励","text":"首次通关精英副本16至19奖励"},{"id":3045,"type":9,"num":0,"name":"帮派商店","text":"帮贡购买帮派商店商品"},{"id":3046,"type":9,"num":0,"name":"活动奖励","text":"圣诞活动期间参与活动获得"},{"id":3047,"type":9,"num":0,"name":"活动奖励","text":"元旦活动期间参与活动获得"},{"id":3048,"type":9,"num":0,"name":"活动奖励","text":"新年活动期间参与活动获得"},{"id":3049,"type":9,"num":0,"name":"活动奖励","text":"元宵活动期间参与活动获得"},{"id":3050,"type":9,"num":0,"name":"积分商店","text":"PVP积分商店随机刷新购买获得"},{"id":3051,"type":9,"num":0,"name":"帮派商店","text":"帮派商店随机刷新购买获得"},{"id":3052,"type":9,"num":0,"name":"神秘商店","text":"神秘商店随机刷新购买获得"},{"id":3053,"type":9,"num":0,"name":"跨服竞技","text":"跨服竞技活动排名奖励获得"},{"id":3054,"type":9,"num":0,"name":"活动奖励","text":"女神节活动期间参与活动获得"},{"id":3055,"type":9,"num":0,"name":"活动奖励","text":"五一节活动期间参与活动获得"}]