[{"id":"ID","randomType":"随机库类型","weight":"单项比重","goodsId":"奖励ID"},{"id":1,"randomType":1,"weight":500,"goodsId":6101},{"id":2,"randomType":1,"weight":333,"goodsId":6102},{"id":3,"randomType":1,"weight":166,"goodsId":6103},{"id":4,"randomType":1,"weight":250,"goodsId":6104},{"id":5,"randomType":1,"weight":166,"goodsId":6105},{"id":6,"randomType":1,"weight":83,"goodsId":6106},{"id":7,"randomType":1,"weight":250,"goodsId":6107},{"id":8,"randomType":1,"weight":166,"goodsId":6108},{"id":9,"randomType":1,"weight":83,"goodsId":6109},{"id":10,"randomType":1,"weight":33,"goodsId":6110},{"id":11,"randomType":1,"weight":33,"goodsId":6111},{"id":12,"randomType":1,"weight":33,"goodsId":6112},{"id":13,"randomType":1,"weight":33,"goodsId":6113},{"id":14,"randomType":1,"weight":33,"goodsId":6114},{"id":15,"randomType":1,"weight":33,"goodsId":6115},{"id":16,"randomType":1,"weight":33,"goodsId":6116},{"id":17,"randomType":1,"weight":33,"goodsId":6117},{"id":18,"randomType":1,"weight":33,"goodsId":6118},{"id":19,"randomType":1,"weight":33,"goodsId":6119},{"id":20,"randomType":1,"weight":33,"goodsId":6120},{"id":21,"randomType":1,"weight":33,"goodsId":6121},{"id":22,"randomType":1,"weight":33,"goodsId":6122},{"id":23,"randomType":1,"weight":33,"goodsId":6123},{"id":24,"randomType":1,"weight":33,"goodsId":6124},{"id":25,"randomType":1,"weight":33,"goodsId":6125},{"id":26,"randomType":1,"weight":33,"goodsId":6126},{"id":27,"randomType":1,"weight":33,"goodsId":6127},{"id":28,"randomType":1,"weight":33,"goodsId":6128},{"id":29,"randomType":1,"weight":33,"goodsId":6129},{"id":30,"randomType":1,"weight":33,"goodsId":6130},{"id":31,"randomType":1,"weight":33,"goodsId":6131},{"id":32,"randomType":1,"weight":33,"goodsId":6132},{"id":33,"randomType":1,"weight":33,"goodsId":6133},{"id":34,"randomType":1,"weight":33,"goodsId":6134},{"id":35,"randomType":1,"weight":33,"goodsId":6135},{"id":36,"randomType":1,"weight":33,"goodsId":6136},{"id":37,"randomType":1,"weight":33,"goodsId":6137},{"id":38,"randomType":1,"weight":33,"goodsId":6138},{"id":39,"randomType":1,"weight":33,"goodsId":6139},{"id":40,"randomType":1,"weight":500,"goodsId":6140},{"id":41,"randomType":1,"weight":333,"goodsId":6141},{"id":42,"randomType":1,"weight":166,"goodsId":6142},{"id":43,"randomType":1,"weight":500,"goodsId":6143},{"id":44,"randomType":1,"weight":333,"goodsId":6144},{"id":45,"randomType":1,"weight":166,"goodsId":6145},{"id":46,"randomType":1,"weight":500,"goodsId":6146},{"id":47,"randomType":1,"weight":333,"goodsId":6147},{"id":48,"randomType":1,"weight":166,"goodsId":6148},{"id":49,"randomType":1,"weight":250,"goodsId":6149},{"id":50,"randomType":1,"weight":166,"goodsId":6150},{"id":51,"randomType":1,"weight":83,"goodsId":6151},{"id":52,"randomType":1,"weight":250,"goodsId":6152},{"id":53,"randomType":1,"weight":166,"goodsId":6153},{"id":54,"randomType":1,"weight":83,"goodsId":6154},{"id":55,"randomType":1,"weight":250,"goodsId":6155},{"id":56,"randomType":1,"weight":166,"goodsId":6156},{"id":57,"randomType":1,"weight":83,"goodsId":6157},{"id":58,"randomType":1,"weight":250,"goodsId":6158},{"id":59,"randomType":1,"weight":166,"goodsId":6159},{"id":60,"randomType":1,"weight":83,"goodsId":6160},{"id":61,"randomType":1,"weight":250,"goodsId":6161},{"id":62,"randomType":1,"weight":166,"goodsId":6162},{"id":63,"randomType":1,"weight":83,"goodsId":6163},{"id":64,"randomType":1,"weight":250,"goodsId":6164},{"id":65,"randomType":1,"weight":166,"goodsId":6165},{"id":66,"randomType":1,"weight":83,"goodsId":6166},{"id":67,"randomType":1,"weight":250,"goodsId":6167},{"id":68,"randomType":1,"weight":166,"goodsId":6168},{"id":69,"randomType":1,"weight":83,"goodsId":6169},{"id":70,"randomType":1,"weight":250,"goodsId":6170},{"id":71,"randomType":1,"weight":166,"goodsId":6171},{"id":72,"randomType":1,"weight":83,"goodsId":6172},{"id":73,"randomType":2,"weight":250,"goodsId":6173},{"id":74,"randomType":2,"weight":250,"goodsId":6174},{"id":75,"randomType":2,"weight":250,"goodsId":6175},{"id":76,"randomType":2,"weight":250,"goodsId":6176},{"id":77,"randomType":2,"weight":250,"goodsId":6177},{"id":78,"randomType":2,"weight":250,"goodsId":6178},{"id":79,"randomType":2,"weight":250,"goodsId":6179},{"id":80,"randomType":2,"weight":250,"goodsId":6180},{"id":81,"randomType":2,"weight":250,"goodsId":6181},{"id":82,"randomType":2,"weight":250,"goodsId":6182},{"id":83,"randomType":2,"weight":250,"goodsId":6183},{"id":84,"randomType":2,"weight":250,"goodsId":6184},{"id":85,"randomType":2,"weight":250,"goodsId":6185},{"id":86,"randomType":2,"weight":250,"goodsId":6186},{"id":87,"randomType":2,"weight":250,"goodsId":6187},{"id":88,"randomType":2,"weight":250,"goodsId":6188},{"id":89,"randomType":2,"weight":250,"goodsId":6189},{"id":90,"randomType":2,"weight":250,"goodsId":6190},{"id":91,"randomType":2,"weight":250,"goodsId":6191},{"id":92,"randomType":2,"weight":250,"goodsId":6192},{"id":93,"randomType":2,"weight":250,"goodsId":6193},{"id":94,"randomType":2,"weight":250,"goodsId":6194},{"id":95,"randomType":2,"weight":250,"goodsId":6195},{"id":96,"randomType":2,"weight":250,"goodsId":6196},{"id":97,"randomType":2,"weight":250,"goodsId":6197},{"id":98,"randomType":2,"weight":250,"goodsId":6198},{"id":99,"randomType":2,"weight":250,"goodsId":6199},{"id":100,"randomType":2,"weight":250,"goodsId":6200},{"id":101,"randomType":2,"weight":250,"goodsId":6201},{"id":102,"randomType":2,"weight":250,"goodsId":6202},{"id":103,"randomType":2,"weight":250,"goodsId":6203},{"id":104,"randomType":2,"weight":250,"goodsId":6204},{"id":105,"randomType":2,"weight":250,"goodsId":6205},{"id":106,"randomType":2,"weight":250,"goodsId":6206},{"id":1001,"randomType":2,"weight":300,"goodsId":6207},{"id":1002,"randomType":2,"weight":300,"goodsId":6208},{"id":1003,"randomType":2,"weight":300,"goodsId":6209},{"id":1004,"randomType":2,"weight":300,"goodsId":6210},{"id":1005,"randomType":2,"weight":300,"goodsId":6211},{"id":2001,"randomType":2,"weight":0,"goodsId":3301},{"id":2002,"randomType":2,"weight":0,"goodsId":3302},{"id":2003,"randomType":2,"weight":0,"goodsId":3303},{"id":2004,"randomType":2,"weight":0,"goodsId":3304},{"id":2005,"randomType":2,"weight":0,"goodsId":3305},{"id":2006,"randomType":2,"weight":0,"goodsId":3306},{"id":2007,"randomType":2,"weight":0,"goodsId":3307},{"id":2008,"randomType":2,"weight":0,"goodsId":3308},{"id":2009,"randomType":2,"weight":0,"goodsId":3309},{"id":2010,"randomType":2,"weight":0,"goodsId":3310},{"id":2011,"randomType":2,"weight":0,"goodsId":3311},{"id":2012,"randomType":2,"weight":0,"goodsId":3312},{"id":2013,"randomType":2,"weight":0,"goodsId":3313},{"id":2014,"randomType":2,"weight":0,"goodsId":3314},{"id":2015,"randomType":2,"weight":0,"goodsId":3315},{"id":2016,"randomType":2,"weight":0,"goodsId":3316},{"id":2017,"randomType":2,"weight":0,"goodsId":3317},{"id":2018,"randomType":2,"weight":0,"goodsId":3318},{"id":2019,"randomType":2,"weight":0,"goodsId":3319},{"id":2020,"randomType":2,"weight":0,"goodsId":3320},{"id":2021,"randomType":2,"weight":0,"goodsId":3321},{"id":2022,"randomType":2,"weight":0,"goodsId":3322},{"id":2023,"randomType":2,"weight":0,"goodsId":3323},{"id":2024,"randomType":2,"weight":0,"goodsId":3324},{"id":2025,"randomType":2,"weight":0,"goodsId":3325},{"id":2026,"randomType":2,"weight":0,"goodsId":3326},{"id":2027,"randomType":2,"weight":0,"goodsId":3327},{"id":2028,"randomType":2,"weight":0,"goodsId":3328},{"id":2029,"randomType":2,"weight":0,"goodsId":3329},{"id":2030,"randomType":2,"weight":0,"goodsId":3330},{"id":2031,"randomType":2,"weight":0,"goodsId":3331},{"id":2032,"randomType":2,"weight":0,"goodsId":3332},{"id":2033,"randomType":2,"weight":0,"goodsId":3333},{"id":2034,"randomType":2,"weight":100,"goodsId":3334},{"id":2035,"randomType":2,"weight":0,"goodsId":3335},{"id":2036,"randomType":2,"weight":0,"goodsId":3336},{"id":2037,"randomType":2,"weight":0,"goodsId":3337},{"id":2038,"randomType":2,"weight":100,"goodsId":3338},{"id":2039,"randomType":2,"weight":100,"goodsId":3339},{"id":2040,"randomType":2,"weight":100,"goodsId":3340},{"id":2041,"randomType":2,"weight":100,"goodsId":3341},{"id":2042,"randomType":2,"weight":100,"goodsId":3342},{"id":2043,"randomType":2,"weight":100,"goodsId":3343},{"id":2044,"randomType":2,"weight":100,"goodsId":3344},{"id":2045,"randomType":2,"weight":100,"goodsId":3345},{"id":2046,"randomType":2,"weight":100,"goodsId":3346},{"id":2047,"randomType":2,"weight":100,"goodsId":3347},{"id":2048,"randomType":2,"weight":100,"goodsId":3348},{"id":2049,"randomType":2,"weight":100,"goodsId":3349},{"id":2050,"randomType":2,"weight":100,"goodsId":3350},{"id":2051,"randomType":2,"weight":100,"goodsId":3351},{"id":2052,"randomType":2,"weight":100,"goodsId":3352}]