[{"id":"ID","type":"任务类型","taskNum1":"任务参数1","taskNum2":"任务参数2","text":"描述","needHeroArray":"上阵英雄限定","nodeText":"觉醒副本描述"},{"id":5001,"type":2,"taskNum1":1183,"taskNum2":3,"text":"三星通关精英副本19-3","needHeroArray":"null","nodeText":"null"},{"id":5002,"type":8,"taskNum1":50,"taskNum2":0,"text":"拥有50个100级英雄(%d/50)","needHeroArray":"null","nodeText":"null"},{"id":5003,"type":11,"taskNum1":20,"taskNum2":0,"text":"拥有20个资质9的英雄(%d/20)","needHeroArray":"null","nodeText":"null"},{"id":5004,"type":9,"taskNum1":30,"taskNum2":0,"text":"拥有30个突破+9的英雄(%d/30)","needHeroArray":"null","nodeText":"null"},{"id":5005,"type":10,"taskNum1":120,"taskNum2":0,"text":"总修炼等级达到120级(%d/120)","needHeroArray":"null","nodeText":"null"},{"id":5006,"type":9,"taskNum1":20,"taskNum2":0,"text":"拥有20个突破+9的英雄(%d/20)","needHeroArray":"null","nodeText":"null"},{"id":5007,"type":8,"taskNum1":40,"taskNum2":0,"text":"拥有40个100级英雄(%d/40)","needHeroArray":"null","nodeText":"null"},{"id":5008,"type":7,"taskNum1":30,"taskNum2":0,"text":"拥有30个橙色英雄(%d/30)","needHeroArray":"null","nodeText":"null"},{"id":5009,"type":2,"taskNum1":1183,"taskNum2":3,"text":"三星通关精英副本19-3","needHeroArray":"null","nodeText":"null"},{"id":5010,"type":8,"taskNum1":30,"taskNum2":0,"text":"拥有30个100级英雄(%d/30)","needHeroArray":"null","nodeText":"null"},{"id":5011,"type":9,"taskNum1":15,"taskNum2":0,"text":"拥有15个突破+9的英雄(%d/15)","needHeroArray":"null","nodeText":"null"},{"id":5012,"type":10,"taskNum1":90,"taskNum2":0,"text":"总修炼等级达到90级(%d/90)","needHeroArray":"null","nodeText":"null"},{"id":5013,"type":10,"taskNum1":100,"taskNum2":0,"text":"总修炼等级达到100级(%d/100)","needHeroArray":"null","nodeText":"null"},{"id":5014,"type":11,"taskNum1":20,"taskNum2":0,"text":"拥有20个资质9的英雄(%d/20)","needHeroArray":"null","nodeText":"null"},{"id":5015,"type":7,"taskNum1":40,"taskNum2":0,"text":"拥有40个橙色英雄(%d/40)","needHeroArray":"null","nodeText":"null"},{"id":5016,"type":2,"taskNum1":1153,"taskNum2":3,"text":"三星通关精英副本16-3","needHeroArray":"null","nodeText":"null"},{"id":5017,"type":5,"taskNum1":100000,"taskNum2":0,"text":"最高战力到达要求(%d/100000)","needHeroArray":"null","nodeText":"null"},{"id":5018,"type":10,"taskNum1":60,"taskNum2":0,"text":"总修炼等级达到60级(%d/60)","needHeroArray":"null","nodeText":"null"},{"id":5019,"type":7,"taskNum1":10,"taskNum2":0,"text":"拥有10个橙色英雄(%d/10)","needHeroArray":"null","nodeText":"null"},{"id":5020,"type":8,"taskNum1":20,"taskNum2":0,"text":"拥有20个100级英雄(%d/20)","needHeroArray":"null","nodeText":"null"},{"id":5021,"type":9,"taskNum1":5,"taskNum2":0,"text":"拥有5个突破+9的英雄(%d/5)","needHeroArray":"null","nodeText":"null"},{"id":5022,"type":10,"taskNum1":80,"taskNum2":0,"text":"总修炼等级达到80级(%d/80)","needHeroArray":"null","nodeText":"null"},{"id":5023,"type":11,"taskNum1":5,"taskNum2":0,"text":"拥有5个资质9的英雄(%d/5)","needHeroArray":"null","nodeText":"null"},{"id":5025,"type":5,"taskNum1":150000,"taskNum2":0,"text":"最高战力到达要求(%d/150000)","needHeroArray":"null","nodeText":"null"},{"id":5026,"type":8,"taskNum1":25,"taskNum2":0,"text":"拥有25个100级英雄(%d/25)","needHeroArray":"null","nodeText":"null"},{"id":5027,"type":7,"taskNum1":15,"taskNum2":0,"text":"拥有15个橙色英雄(%d/15)","needHeroArray":"null","nodeText":"null"},{"id":5028,"type":8,"taskNum1":30,"taskNum2":0,"text":"拥有30个100级英雄(%d/30)","needHeroArray":"null","nodeText":"null"},{"id":5029,"type":9,"taskNum1":15,"taskNum2":0,"text":"拥有15个突破+9的英雄(%d/15)","needHeroArray":"null","nodeText":"null"},{"id":5030,"type":10,"taskNum1":90,"taskNum2":0,"text":"总修炼等级达到90级(%d/90)","needHeroArray":"null","nodeText":"null"},{"id":5031,"type":11,"taskNum1":10,"taskNum2":0,"text":"拥有10个资质9的英雄(%d/10)","needHeroArray":"null","nodeText":"null"},{"id":5032,"type":2,"taskNum1":1183,"taskNum2":3,"text":"三星通关精英副本19-3","needHeroArray":"null","nodeText":"null"},{"id":5033,"type":5,"taskNum1":200000,"taskNum2":0,"text":"最高战力到达要求(%d/200000)","needHeroArray":"null","nodeText":"null"},{"id":5034,"type":11,"taskNum1":15,"taskNum2":0,"text":"拥有15个资质9的英雄(%d/15)","needHeroArray":"null","nodeText":"null"},{"id":5035,"type":7,"taskNum1":30,"taskNum2":0,"text":"拥有30个橙色英雄(%d/30)","needHeroArray":"null","nodeText":"null"},{"id":5036,"type":8,"taskNum1":40,"taskNum2":0,"text":"拥有40个100级英雄(%d/40)","needHeroArray":"null","nodeText":"null"},{"id":5037,"type":9,"taskNum1":25,"taskNum2":0,"text":"拥有25个突破+9的英雄(%d/25)","needHeroArray":"null","nodeText":"null"},{"id":5038,"type":10,"taskNum1":110,"taskNum2":0,"text":"总修炼等级达到110级(%d/110)","needHeroArray":"null","nodeText":"null"},{"id":5039,"type":11,"taskNum1":15,"taskNum2":0,"text":"拥有15个资质9的英雄(%d/15)","needHeroArray":"null","nodeText":"null"},{"id":5040,"type":2,"taskNum1":1183,"taskNum2":3,"text":"三星通关精英副本19-3","needHeroArray":"null","nodeText":"null"},{"id":5041,"type":5,"taskNum1":250000,"taskNum2":0,"text":"最高战力到达要求(%d/250000)","needHeroArray":"null","nodeText":"null"},{"id":5042,"type":10,"taskNum1":100,"taskNum2":0,"text":"总修炼等级达到100级(%d/100)","needHeroArray":"null","nodeText":"null"},{"id":5043,"type":7,"taskNum1":40,"taskNum2":0,"text":"拥有40个橙色英雄(%d/40)","needHeroArray":"null","nodeText":"null"},{"id":5044,"type":8,"taskNum1":50,"taskNum2":0,"text":"拥有50个100级英雄(%d/50)","needHeroArray":"null","nodeText":"null"},{"id":5045,"type":9,"taskNum1":30,"taskNum2":0,"text":"拥有30个突破+9的英雄(%d/30)","needHeroArray":"null","nodeText":"null"},{"id":6001,"type":4,"taskNum1":7001,"taskNum2":0,"text":"通关变异律法女娲觉醒副本","needHeroArray":"5561|3|3;4801|3|1;7341|2|2;7461|1|1;7481|1|3","nodeText":"变异律法女娲觉醒，世间沧海可幻为桑田，唯有真律庚古未变，三大菩萨倾力相助，勘破世间虚幻，看透天地无常。"},{"id":6002,"type":4,"taskNum1":7002,"taskNum2":0,"text":"通关灵吉菩萨觉醒副本","needHeroArray":"7301|2|1;7541|2|2;7321|2|3;7361|1|1;5621|1|3","nodeText":"灵吉菩萨觉醒，三界众神齐来见证，过去佛燃灯老祖、地仙之首镇元子、三清之列太上老君，更有身份玄妙的神秘人。"},{"id":6003,"type":4,"taskNum1":7003,"taskNum2":0,"text":"通关观音菩萨觉醒副本","needHeroArray":"5561|3|3;4801|3|1;7341|2|2;4861|1|1;4841|1|3","nodeText":"观音菩萨觉醒，度化世人如度自身，如肯回头何劳吾救苦救难，若能转念无须我大慈大悲。"},{"id":6004,"type":4,"taskNum1":7004,"taskNum2":0,"text":"通关如来觉醒副本","needHeroArray":"7501|3|1;7521|3|3;7441|1|2;7461|1|1;7481|1|3","nodeText":"如来觉醒，大雪山再正金身，文殊菩萨、普贤菩萨左右协侍，降龙罗汉、伏虎罗汉左右护法。"},{"id":6005,"type":4,"taskNum1":7005,"taskNum2":0,"text":"通关斗战胜佛觉醒副本","needHeroArray":"5661|3|2;5581|2|1;7541|2|2;7621|2|3;5521|1|2","nodeText":"斗战胜佛觉醒，过去佛燃灯与金翅大鹏明王前来助力，又有当年大闹天宫的齐天大圣分身和得力后辈暴力猴相帮。"},{"id":6006,"type":4,"taskNum1":7006,"taskNum2":0,"text":"通关哪吒觉醒副本","needHeroArray":"5261|3|2;7501|3|1;7521|3|3;7461|1|1;7481|1|3","nodeText":"哪吒觉醒，两朵莲花现化身，灵珠二世出凡尘。手提紫焰蛇矛宝；脚踏金霞风火轮。"},{"id":6007,"type":4,"taskNum1":7007,"taskNum2":0,"text":"通关天使夜罗刹觉醒副本","needHeroArray":"5421|3|1;7521|3|3;7301|2|1;7321|2|3;5361|2|2","nodeText":"天使夜罗刹觉醒，本是食人妖魔生，难得悟道天地成，褪去精怪皮囊相，祥光万道罗刹行。"},{"id":6008,"type":4,"taskNum1":7008,"taskNum2":0,"text":"通关黄牙老象觉醒副本","needHeroArray":"5501|3|3;5521|1|2;5541|3|2;7501|3|1;7341|2|2","nodeText":"黄牙老象觉醒，凤目金睛，黄牙粗腿，长鼻银毛，身躯磊磊，鼻似蛟龙，铁背铜身，普贤座驾六牙神象现身。"},{"id":6009,"type":4,"taskNum1":7009,"taskNum2":0,"text":"通关金翅大鹏雕觉醒副本","needHeroArray":"5521|1|2;5541|3|2;5501|3|3;7501|3|1;7341|2|2","nodeText":"金翅大鹏雕觉醒，抟风翮百鸟藏头，舒利爪诸禽丧胆。如来见我需顿首，迦楼罗王现真身。"},{"id":6010,"type":4,"taskNum1":7010,"taskNum2":0,"text":"通关青毛狮王觉醒副本","needHeroArray":"5541|3|2;5501|3|3;7341|2|2;5581|2|1;5521|1|2","nodeText":"青毛狮王觉醒，铁额铜头戴宝盔，盔缨飘舞甚光辉。辉辉掣电双睛亮，亮亮铺霞两鬓飞。"},{"id":6011,"type":4,"taskNum1":7011,"taskNum2":0,"text":"通关释迦牟尼觉醒副本","needHeroArray":"5641|2|2;7501|3|1;7521|3|3;7461|1|1;7481|1|3","nodeText":"迦毗罗王子释迦牟尼觉醒，未香以涂身，并熏衣缨络，倒惑心亦尔，谓从已身出，如彼丑陋婢，见影谓已有。"},{"id":6012,"type":4,"taskNum1":7012,"taskNum2":0,"text":"通关暴力猴觉醒副本","needHeroArray":"5661|3|2;7501|3|1;7521|3|3;5581|2|1;7321|2|3","nodeText":"暴力猴觉醒，通晓阴阳会人理，避死延生百变化。暴力堪敌九恶龙，善通八卦风水流。"},{"id":6013,"type":4,"taskNum1":7013,"taskNum2":0,"text":"通关嫦娥仙子觉醒副本","needHeroArray":"5681|2|2;7501|3|1;7521|3|3;5261|3|2;5521|1|2","nodeText":"月神太阴星君嫦娥仙子觉醒，白兔捣药秋复春，嫦娥孤栖与谁邻，今人不见古时月，今月曾经照古人。"},{"id":6014,"type":4,"taskNum1":7014,"taskNum2":0,"text":"通关弥勒佛觉醒副本","needHeroArray":"7401|1|1;7501|3|1;7521|3|3;7541|2|2;7481|1|3","nodeText":"未来之佛弥勒佛觉醒，皆大欢喜，春风满面常开口。了无挂碍，世态撩人不改容。"},{"id":6015,"type":4,"taskNum1":7015,"taskNum2":0,"text":"通关毗蓝婆菩萨觉醒副本","needHeroArray":"7421|1|3;7501|3|1;7521|3|3;7461|1|1;7541|2|2","nodeText":"星官之母毗蓝婆菩萨觉醒，家住紫云千花洞，绣花神针降妖魔，为偿宿劫愿，浩荡向前行。"},{"id":6016,"type":4,"taskNum1":7016,"taskNum2":0,"text":"通关旃檀功德佛觉醒副本","needHeroArray":"7501|3|1;7561|2|2;7521|3|3;7461|1|1;7481|1|3","nodeText":"灵通本讳号金蝉，转托尘凡苦受磨，明心解养人天法，见性能传智慧灯，诚为佛子不虚传，一心只为众苍生。"},{"id":6017,"type":4,"taskNum1":7017,"taskNum2":0,"text":"通关美猴王觉醒副本","needHeroArray":"7521|3|3;7341|2|2;7501|3|1;7461|1|1;7481|1|3","nodeText":"身穿金甲亮堂堂，头戴金冠光映映，手举定海金箍棒，足踏云履四海平，花果水帘真福地，猴王美名三界明。"},{"id":6018,"type":4,"taskNum1":7018,"taskNum2":0,"text":"通关净坛使者觉醒副本","needHeroArray":"7461|1|1;7341|2|2;7501|3|1;7521|3|3;7481|1|3","nodeText":"九齿钉耙帅天河，无端酒醉戏嫦娥，高老庄前锄广野，白龙马后挑簸箩，难寻真爱心愈屈，一路彷徨未成佛。"},{"id":6019,"type":4,"taskNum1":7019,"taskNum2":0,"text":"通关金身罗汉觉醒副本","needHeroArray":"7481|1|3;7561|2|2;7501|3|1;7521|3|3;7461|1|1","nodeText":"位列仙班志未伸，琉璃盏碎值几文，无端落草流沙界，歇去狂骨见佛心，纵使见思今悟净，才得如来一分真。"},{"id":6020,"type":4,"taskNum1":7020,"taskNum2":0,"text":"通关八部天龙觉醒副本","needHeroArray":"7361|1|1;7341|2|2;7321|2|3;7301|2|1;7481|1|3","nodeText":"江海遨游已成梦，何辜白马啸西风，拘羁缘起明珠劫，护法恣奔天竺空，重铸金身非太子，久缠华表金天龙。"},{"id":6021,"type":4,"taskNum1":7021,"taskNum2":0,"text":"通关金角大王觉醒副本","needHeroArray":"4961|2|1;4981|2|3;5601|1|1;5221|2|2;5621|1|3","nodeText":"圆眼睁开光掣电，钢须飘起乱飞烟，阴阳宝瓶轻提手，芭蕉扇子半遮肩，威风凛凛欺天将，声如霹雳震山川。"},{"id":6022,"type":4,"taskNum1":7022,"taskNum2":0,"text":"通关银角大王觉醒副本","needHeroArray":"4981|2|3;4961|2|1;5601|1|1;5221|2|2;5621|1|3","nodeText":"头戴凤盔欺腊雪，身披战甲幌镔铁，颜如灌口活真君，貌比巨灵无二别，七星宝剑手中擎，怒气冲霄威烈烈。"},{"id":6023,"type":4,"taskNum1":7023,"taskNum2":0,"text":"通关独角兕大王觉醒副本","needHeroArray":"5021|3|2;4881|2|2;5521|1|2;5621|1|3;7381|1|1","nodeText":"毛皮青似靛，筋挛硬如钢，雄威直挺点钢枪，倒有欺天振地强，细看这等凶模样，不枉名称兕大王。"},{"id":6025,"type":4,"taskNum1":7025,"taskNum2":0,"text":"通关铁扇公主觉醒副本","needHeroArray":"5061|3|3;5081|2|3;5281|2|2;5581|2|1;5621|1|3","nodeText":"头裹团花帕，身穿纳云袍，腰间双束虎筋绦，微露绣裙偏绡，手提宝剑怒声高，堪比嫦娥容美貌。"},{"id":6026,"type":4,"taskNum1":7026,"taskNum2":0,"text":"通关白骨精觉醒副本","needHeroArray":"5181|2|2;5221|1|2;5621|1|3;7381|1|1;5421|3|2","nodeText":"本已成枯骨，重吸日月精，扶摇惊落雪，步履隐香风，结印莲花手，读经宝罄声，青眸凝厉色，幽怨待唐僧。"},{"id":6027,"type":4,"taskNum1":7027,"taskNum2":0,"text":"通关二郎神觉醒副本","needHeroArray":"5241|3|2;7341|2|2;5521|1|2;7301|2|1;7321|2|3","nodeText":"斧劈桃山曾救母，手执三尖两刃枪，义结梅山七圣行，性傲归神住灌江，赤城昭惠英灵圣，显化无边号二郎。"},{"id":6028,"type":4,"taskNum1":7028,"taskNum2":0,"text":"通关红孩儿觉醒副本","needHeroArray":"5061|3|3;5081|2|3;5281|2|2;5581|2|1;5621|1|3","nodeText":"双手绰枪威凛冽，祥光护体出门来，哏声响若春雷吼，暴眼明如掣电乖，要识此魔真姓氏，名扬千古唤红孩。"},{"id":6029,"type":4,"taskNum1":7029,"taskNum2":0,"text":"通关转世蚩尤觉醒副本","needHeroArray":"5481|3|1;5461|2|1;5601|1|1;7341|2|2;7321|2|3","nodeText":"上古战神骁战勇，九黎部族推英雄，铜头铁臂率部众，敢于皇帝争天下，逐鹿之战身虽死，战神名号三界擎。"},{"id":6030,"type":4,"taskNum1":7030,"taskNum2":0,"text":"通关转世刑天觉醒副本","needHeroArray":"5481|3|1;5461|2|1;5601|1|1;7341|2|2;7321|2|3","nodeText":"羊常山下一巨人，炎帝大将做先锋，惨被皇帝身首异，以乳为目脐为口，常舞干戚于天际，猛志常在乾坤行。"},{"id":6031,"type":4,"taskNum1":7031,"taskNum2":0,"text":"通关齐天大圣觉醒副本","needHeroArray":"5581|2|1;7341|2|2;7321|2|3;7381|1|1;5621|1|3","nodeText":"四海名扬花果山，自封大圣可齐天，筋斗云纵十万里，金箍棒舞鬼魔寒，恰逢王母天仙会，如今致有祸桃园。"},{"id":6032,"type":4,"taskNum1":7032,"taskNum2":0,"text":"通关转世祝融觉醒副本","needHeroArray":"5481|3|1;5461|2|1;5601|1|1;7341|2|2;7321|2|3","nodeText":"上古火神贤帝王，以火施化号赤帝，高山奏曲感肺腑，黎民百姓情高昂，真火斗败水共工，星火燎原美名扬。"},{"id":6033,"type":4,"taskNum1":7033,"taskNum2":0,"text":"通关神秘人觉醒副本","needHeroArray":"7501|3|1;7521|3|3;7441|1|2;7461|1|1;7481|1|3","nodeText":"身披斗篷不见真容，来去无影行走无声，神龙见首不见尾，真身见形不见影，试问哪一位，且看言与行。"},{"id":6034,"type":4,"taskNum1":7034,"taskNum2":0,"text":"通关太上老君觉醒副本","needHeroArray":"7321|2|3;7341|2|2;7301|2|1;7501|3|1;7521|3|3","nodeText":"三清之首李老君，兜率天宫修为深，混元初判道为尊，炼就乾坤清浊分，太极两仪生四象，如今还在掌中存。"},{"id":6035,"type":4,"taskNum1":7035,"taskNum2":0,"text":"通关镇元大仙觉醒副本","needHeroArray":"7361|1|1;7341|2|2;7321|2|3;7301|2|1;7481|1|3","nodeText":"地仙之祖仙，头戴紫金冠，履鞋登足下，丝带束腰间。体如童子貌，面似美人颜。三须飘颔下，鸦翎叠鬓边。"},{"id":6036,"type":4,"taskNum1":7036,"taskNum2":0,"text":"通关太白金星觉醒副本","needHeroArray":"7381|1|1;7341|2|2;7321|2|3;7301|2|1;7481|1|3","nodeText":"太白长庚星，玉帝信使行，鹤发童颜带拂尘，腾云驾雾三界行，传达谕旨宣仙界，抚平诸教众纷争。"},{"id":6037,"type":4,"taskNum1":7037,"taskNum2":0,"text":"通关文殊菩萨觉醒副本","needHeroArray":"7461|1|1;7341|2|2;7501|3|1;7521|3|3;7481|1|3","nodeText":"文殊菩萨德难量，久成龙种上法王，因怜众生迷自性，特辅释迦振玄纲，佛家智慧般若深，无上正等觉法高。"},{"id":6038,"type":4,"taskNum1":7038,"taskNum2":0,"text":"通关普贤菩萨觉醒副本","needHeroArray":"7481|1|3;7561|2|2;7501|3|1;7521|3|3;7461|1|1","nodeText":"大行菩萨称普贤，重重愿海浩无边，端严示坐六牙象，智慧化生七宝莲，一切三昧皆自在，灵感神通震大千。"},{"id":6039,"type":4,"taskNum1":7039,"taskNum2":0,"text":"通关伏虎罗汉觉醒副本","needHeroArray":"7501|3|1;7561|2|2;7521|3|3;7461|1|1;7481|1|3","nodeText":"十八罗汉伏虎僧，门前饿虎啸声声，弥勒慈悲饭食迎，佛法应能平兽性，菩提大道向西去，正得金身伴佛行。"},{"id":6040,"type":4,"taskNum1":7040,"taskNum2":0,"text":"通关降龙罗汉觉醒副本","needHeroArray":"7521|3|3;7341|2|2;7501|3|1;7461|1|1;7481|1|3","nodeText":"罗汉魁首善降龙，修来正果度金身，七世尘缘未了情，下凡渡众止刀兵，龙降经取妖氛散，迦叶功高博颂声。"},{"id":6041,"type":4,"taskNum1":7041,"taskNum2":0,"text":"通关燃灯古佛觉醒副本","needHeroArray":"7541|2|2;7401|1|1;5621|1|3;5521|1|2;5421|3|2","nodeText":"上古庄严劫所生的千佛之首，身如明灯照三界，点悟释迦摩尼，万佛之师。"},{"id":6042,"type":4,"taskNum1":7042,"taskNum2":0,"text":"通关药师佛觉醒副本","needHeroArray":"7561|2|2;7401|1|1;5621|1|3;5521|1|2;5421|3|2","nodeText":"愿我来世得阿耨多罗三藐三菩提时，自身光明炽然，照耀无量无数无边世界，身如琉璃净无秽，诸行有情悟大乘。"},{"id":6043,"type":4,"taskNum1":7043,"taskNum2":0,"text":"通关地藏菩萨觉醒副本","needHeroArray":"7581|3|1;7561|2|2;5621|1|3;7461|1|1;7441|1|2","nodeText":"安忍不动，犹如大地，静虑深密，犹如秘藏，为救地狱受苦的母亲，发愿救度一切地府罪苦众生，地狱不空不成佛。"},{"id":6044,"type":4,"taskNum1":7044,"taskNum2":0,"text":"通关大日如来觉醒副本","needHeroArray":"7601|3|3;7401|1|1;7541|2|2;7481|1|3;5521|1|2","nodeText":"释迦牟尼三身佛之一，绝对真理的化身佛，智慧之光遍照一切光明处，能通天地之灵气，善取万物之精华。"},{"id":6045,"type":4,"taskNum1":7045,"taskNum2":0,"text":"通关菩提老祖觉醒副本","needHeroArray":"7641|1|3;7341|2|2;5581|2|1;5661|3|2;5601|1|1","nodeText":"身居灵台方寸山，修行斜月三星洞，大觉金仙无垢姿，西方妙相祖菩提，不生不灭三三行，全气全神万万慈。"}]